kirt08_contracts/__init__.py
kirt08_contracts/auth_pb2.py
kirt08_contracts/auth_pb2_grpc.py
kirt08_contracts-0.1.4.dist-info/METADATA
kirt08_contracts-0.1.4.dist-info/WHEEL
kirt08_contracts-0.1.4.dist-info/RECORD
