Metadata-Version: 2.4
Name: kirt08_contracts
Version: 0.1.4
Summary: 
Author: romanov.da
Author-email: dimromgomell@gmail.com
Requires-Python: >=3.12, <3.13
Classifier: Programming Language :: Python :: 3
Classifier: Programming Language :: Python :: 3.12
Requires-Dist: grpcio (>=1.76.0,<2.0.0)
Requires-Dist: grpcio-tools (>=1.76.0,<2.0.0)
Requires-Dist: protobuf (>=6.33.4,<7.0.0)
